odoo/addons/sale_channel_category/README.rst
odoo/addons/sale_channel_category/__init__.py
odoo/addons/sale_channel_category/__manifest__.py
odoo/addons/sale_channel_category/i18n/it.po
odoo/addons/sale_channel_category/i18n/sale_channel_category.pot
odoo/addons/sale_channel_category/models/__init__.py
odoo/addons/sale_channel_category/models/product_category.py
odoo/addons/sale_channel_category/models/sale_channel.py
odoo/addons/sale_channel_category/readme/CONTRIBUTORS.md
odoo/addons/sale_channel_category/readme/DESCRIPTION.md
odoo/addons/sale_channel_category/static/description/icon.png
odoo/addons/sale_channel_category/static/description/index.html
odoo/addons/sale_channel_category/tests/__init__.py
odoo/addons/sale_channel_category/tests/test_sale_channel.py
odoo/addons/sale_channel_category/views/product_category_view.xml
odoo/addons/sale_channel_category/views/sale_channel_view.xml
odoo_addon_sale_channel_category-18.0.1.0.0.3.dist-info/METADATA
odoo_addon_sale_channel_category-18.0.1.0.0.3.dist-info/WHEEL
odoo_addon_sale_channel_category-18.0.1.0.0.3.dist-info/top_level.txt
odoo_addon_sale_channel_category-18.0.1.0.0.3.dist-info/RECORD
